README.md
coosa_control.py
setup.py
coosa_control.egg-info/PKG-INFO
coosa_control.egg-info/SOURCES.txt
coosa_control.egg-info/dependency_links.txt
coosa_control.egg-info/entry_points.txt
coosa_control.egg-info/requires.txt
coosa_control.egg-info/top_level.txt