Metadata-Version: 1.1
Name: coosa-control
Version: 0.1.0
Summary: Control script for coosa smart plugs
Home-page: https://github.com/matthewscholefield/coosa-control
Author: Matthew D. Scholefield
Author-email: matthew331199@gmail.com
License: UNKNOWN
Keywords: coosa control
Platform: UNKNOWN
Classifier: Development Status :: 3 - Alpha
Classifier: Intended Audience :: Developers
Classifier: Programming Language :: Python :: 3
Classifier: Programming Language :: Python :: 3.4
Classifier: Programming Language :: Python :: 3.5
Classifier: Programming Language :: Python :: 3.6
